Workbook

Sheet - AYUDA -
B4: Ayuda

Sheet Precios 
B5: Comparación de Precios entre diferentes proveedores
B6: Ingresa en la tabla los productos, los proveedores y sus precios
J7: ESTADÍSTICAS POR PRODUCTO
B8: PRODUCTO | C8: CANTIDAD | D8: PROVEEDOR 1 | E8: PROVEEDOR 2 | F8: PROVEEDOR 3 | G8: PROVEEDOR 4 | H8: PROVEEDOR 5 | I8: PROVEEDOR 6 | J8: PRECIO MÁS BAJO | K8: PRECIO PROMEDIO | L8: PRECIO MÁS ALTO
B9: Torre admin | C9: 1 | D9: 827050 | E9: 1011500 | F9: 1368500 | J9: =MIN('Precios '!$D9:$I9) -> 827050 | K9: =IFERROR(AVERAGE('Precios '!$D9:$I9),0) -> 1069016.7 | L9: =MAX('Precios '!$D9:$I9) -> 1368500
B10: Monitor Admin | C10: 1 | D10: 135907 | E10: 132810 | F10: 227981 | J10: =MIN('Precios '!$D10:$I10) -> 132810 | K10: =IFERROR(AVERAGE('Precios '!$D10:$I10),0) -> 165566 | L10: =MAX('Precios '!$D10:$I10) -> 227981
B11: Disco Solido Admin | C11: 1 | D11: 214081 | E11: 392581 | F11: 296310 | J11: =MIN('Precios '!$D11:$I11) -> 214081 | K11: =IFERROR(AVERAGE('Precios '!$D11:$I11),0) -> 300990.67 | L11: =MAX('Precios '!$D11:$I11) -> 392581
B12: Disco Duro Interno Admin | C12: 1 | D12: 225981 | E12: 238000 | F12: 398650 | J12: =MIN('Precios '!$D12:$I12) -> 225981 | K12: =IFERROR(AVERAGE('Precios '!$D12:$I12),0) -> 287543.67 | L12: =MAX('Precios '!$D12:$I12) -> 398650
B13: Servidor Admin | C13: 1 | D13: 5710001 | E13: 7000000 | F13: 10571799 | J13: =MIN('Precios '!$D13:$I13) -> 5710001 | K13: =IFERROR(AVERAGE('Precios '!$D13:$I13),0) -> 7760600 | L13: =MAX('Precios '!$D13:$I13) -> 10571799
B14: Ram Admin | C14: 1 | D14: 213099 | E14: 297500 | F14: 289170 | J14: =MIN('Precios '!$D14:$I14) -> 213099 | K14: =IFERROR(AVERAGE('Precios '!$D14:$I14),0) -> 266589.67 | L14: =MAX('Precios '!$D14:$I14) -> 297500
B15: Mouse Admin | C15: 1 | D15: 23900 | E15: 93000 | F15: 138674 | J15: =MIN('Precios '!$D15:$I15) -> 23900 | K15: =IFERROR(AVERAGE('Precios '!$D15:$I15),0) -> 85191.333 | L15: =MAX('Precios '!$D15:$I15) -> 138674
B16: Teclado Admin | C16: 1 | D16: 83181 | E16: 190281 | F16: 142681 | J16: =MIN('Precios '!$D16:$I16) -> 83181 | K16: =IFERROR(AVERAGE('Precios '!$D16:$I16),0) -> 138714.33 | L16: =MAX('Precios '!$D16:$I16) -> 190281
B17: Licencia Windows 11 | C17: 1 | D17: 41531 | E17: 59381 | F17: 142681 | J17: =MIN('Precios '!$D17:$I17) -> 41531 | K17: =IFERROR(AVERAGE('Precios '!$D17:$I17),0) -> 81197.667 | L17: =MAX('Precios '!$D17:$I17) -> 142681
J20: =SUM(J9:J19) -> 7471634 | K20: =SUM(K6:K19) -> 10155410 | L20: =SUM(L9:L19) -> 13728647
B26: Total | D26: =ROUND(SUMPRODUCT('Precios '!$C$9:$C$25,'Precios '!$D$9:$D$25),2) -> 7474731 | E26: =ROUND(SUMPRODUCT('Precios '!$C$9:$C$25,'Precios '!$E$9:$E$25),2) -> 9415053 | F26: =ROUND(SUMPRODUCT('Precios '!$C$9:$C$25,'Precios '!$F$9:$F$25),2) -> 13576446 | G26: =ROUND(SUMPRODUCT('Precios '!$C$9:$C$25,'Precios '!$G$9:$G$25),2) -> 0 | H26: =ROUND(SUMPRODUCT('Precios '!$C$9:$C$25,'Precios '!$H$9:$H$25),2) -> 0 | I26: =ROUND(SUMPRODUCT('Precios '!$C$9:$C$25,'Precios '!$I$9:$I$25),2) -> 0
B29: DATOS ADICIONALES
B30: TIEMPO DE ENTREGA (DÍAS) | D30: Horas de dia los 7 dias de la semana | E30: de 3 a 5 minutos | F30: 3 a 10 dias habiles | G30: entrega de 2 dias habiles | H30: 1 a 5 dias habiles | I30: 5 dias laborales
B31: COSTO DE ENVÍO | D31: 0 | E31: $ 7.055 | F31: $287.497 | G31: 0 | H31: $295.39 | I31: 0
B32: FORMAS DE PAGO
D34: contado | E34: contado | F34: contado | G34: contado | H34: contado | I34: contado

Sheet Precios  (2)
B5: Comparación de Precios entre diferentes proveedores
B6: Ingresa en la tabla los productos, los proveedores y sus precios
J7: ESTADÍSTICAS POR PRODUCTO
B8: PRODUCTO | C8: CANTIDAD | D8: PROVEEDOR 1 | E8: PROVEEDOR 2 | F8: PROVEEDOR 3 | G8: PROVEEDOR 4 | H8: PROVEEDOR 5 | I8: PROVEEDOR 6 | J8: PRECIO MÁS BAJO | K8: PRECIO PROMEDIO | L8: PRECIO MÁS ALTO
B9: Portatil Nosotros | C9: 1 | D9: 1903881 | E9: 2379881 | F9: 2974881 | J9: =MIN(D9:F9) -> 1903881 | K9: =IFERROR(AVERAGE('Precios (2)'!$D9:$I9),0) -> 2419547.7 | L9: =MAX('Precios (2)'!$D9:$I9) -> 2974881
B10: Monitor Nosotros | C10: 1 | D10: 831810 | E10: 595000 | F10: 523481 | J10: =MIN(D10:F10) -> 523481 | K10: =IFERROR(AVERAGE('Precios (2)'!$D10:$I10),0) -> 650097 | L10: =MAX('Precios (2)'!$D10:$I10) -> 831810
B11: Disco Duro Mecanico Nosotros | C11: 1 | D11: 289919 | E11: 304888 | F11: 263224 | J11: =MIN(D11:F11) -> 263224 | K11: =IFERROR(AVERAGE('Precios (2)'!$D11:$I11),0) -> 286010.33 | L11: =MAX('Precios (2)'!$D11:$I11) -> 304888
B12: Ram Nosotros | C12: 1 | D12: 213010 | E12: 202300 | F12: 202300 | J12: =MIN(D12:F12) -> 202300 | K12: =IFERROR(AVERAGE('Precios (2)'!$D12:$I12),0) -> 205870 | L12: =MAX('Precios (2)'!$D12:$I12) -> 213010
B13: Servidor Nosotros | C13: 1 | D13: 1666000 | E13: 928200 | F13: 1428000 | J13: =MIN(D13:F13) -> 928200 | K13: =IFERROR(AVERAGE('Precios (2)'!$D13:$I13),0) -> 1340733.3 | L13: =MAX('Precios (2)'!$D13:$I13) -> 1666000
B14: Tarjeta de Video Nosotros | C14: 1 | D14: 141610 | E14: 248710 | F14: 130900 | J14: =MIN(D14:F14) -> 130900 | K14: =IFERROR(AVERAGE('Precios (2)'!$D14:$I14),0) -> 173740 | L14: =MAX('Precios (2)'!$D14:$I14) -> 248710
B15: Procesador Nosotros | C15: 1 | D15: 291500 | E15: 310102 | F15: 422083 | J15: =MIN(D15:F15) -> 291500 | K15: =IFERROR(AVERAGE('Precios (2)'!$D15:$I15),0) -> 341228.33 | L15: =MAX('Precios (2)'!$D15:$I15) -> 422083
B16: Teclado Nosotros | C16: 1 | D16: 139468 | E16: 60095 | F16: 100436 | J16: =MIN(D16:F16) -> 60095 | K16: =IFERROR(AVERAGE('Precios (2)'!$D16:$I16),0) -> 99999.667 | L16: =MAX('Precios (2)'!$D16:$I16) -> 139468
B17: Mouse Nosotros | C17: 1 | D17: 23900 | E17: 93000 | F17: 138674 | J17: =MIN(D17:F17) -> 23900 | K17: =IFERROR(AVERAGE('Precios (2)'!$D17:$I17),0) -> 85191.333 | L17: =MAX('Precios (2)'!$D17:$I17) -> 138674
B18: Licencia Software | C18: 1 | D18: 0 | E18: 3375506 | F18: 0 | J18: =MIN(D18:F18) -> 0 | K18: =IFERROR(AVERAGE('Precios (2)'!$D18:$I18),0) -> 1125168.7 | L18: =MAX('Precios (2)'!$D18:$I18) -> 3375506
B19: Licencia Visual | C19: 1 | D19: 0 | E19: 668127 | F19: 960021 | J19: =MIN(D19:F19) -> 0 | K19: =IFERROR(AVERAGE('Precios (2)'!$D19:$I19),0) -> 542716 | L19: =MAX('Precios (2)'!$D19:$I19) -> 960021
B20: Licencia Windows 11 | C20: 1 | D20: 51158 | E20: 99001 | F20: 56525 | J20: =MIN(D20:F20) -> 51158 | K20: =IFERROR(AVERAGE('Precios (2)'!$D20:$I20),0) -> 68894.667 | L20: =MAX('Precios (2)'!$D20:$I20) -> 99001
B21: Licencia SQL | C21: 1 | D21: 0 | E21: 4666832 | F21: 1790434 | J21: =MIN(D21:F21) -> 0 | K21: =IFERROR(AVERAGE('Precios (2)'!$D21:$I21),0) -> 2152422 | L21: =MAX('Precios (2)'!$D21:$I21) -> 4666832
J22: =H23
J23: =SUM(J9:J21) -> 4378639 | K23: =SUM(K6:K21) -> 9491619 | L23: =SUM(L6:L21) -> 16040884
B25: Total | D25: =ROUND(SUMPRODUCT('Precios (2)'!$C$9:$C$24,'Precios (2)'!$D$9:$D$24),2) -> 5552256 | E25: =ROUND(SUMPRODUCT('Precios (2)'!$C$9:$C$24,'Precios (2)'!$E$9:$E$24),2) -> 13931642 | F25: =ROUND(SUMPRODUCT('Precios (2)'!$C$9:$C$24,'Precios (2)'!$F$9:$F$24),2) -> 8990959 | G25: =ROUND(SUMPRODUCT('Precios (2)'!$C$9:$C$24,'Precios (2)'!$G$9:$G$24),2) -> 0 | H25: =ROUND(SUMPRODUCT('Precios (2)'!$C$9:$C$24,'Precios (2)'!$H$9:$H$24),2) -> 0 | I25: =ROUND(SUMPRODUCT('Precios (2)'!$C$9:$C$24,'Precios (2)'!$I$9:$I$24),2) -> 0
B28: DATOS ADICIONALES
B29: TIEMPO DE ENTREGA (DÍAS)
B30: COSTO DE ENVÍO
B31: FORMAS DE PAGO

Sheet Soporte
B7: Almendras | C7: 1 | D7: 498 | E7: 420 | F7: 450 | G7: 230 | H7: 600 | I7: 520
B8: Nueces | C8: 2 | D8: 450 | E8: 220 | F8: 405 | G8: 495 | H8: 540 | I8: 200
B9: Pistachos | C9: 2 | D9: 650 | E9: 620 | F9: 666 | G9: 400 | H9: 648 | I9: 452.4
B10: Pecán | C10: 1 | D10: 585 | E10: 558 | F10: 320 | G10: 360 | H10: 583.2 | I10: 407.16
B11: Bananas | C11: 3 | D11: 526.5 | E11: 502.2 | F11: 539.46 | G11: 300 | H11: 500 | I11: 366.44
B12: Pasas | C12: 1 | D12: 473.8 | E12: 200 | F12: 485.51 | G12: 291.6 | H12: 270 | I12: 220
D19: 30 | E19: 10 | F19: 15 | G19: 15 | H19: 15 | I19: 10
D20: 10 | E20: 10 | F20: 10 | G20: Gratis | H20: 5 | I20: Gratis
D21: Efvo | E21: Efvo | F21: Mercado Pago | G21: Efectivo | H21: Mercado Pago | I21: Mercado Pago
D22: Tarjeta | E22: Tarjeta | F22: Tarjeta cuotas | G22: Mercado Pago | H22: Tarjeta cuotas | I22: Tarjeta cuotas
B28: Piñones | C28: 1 | D28: 340 | E28: 330 | F28: 440 | G28: 400 | H28: 320 | I28: 330
B29: Cranberries | C29: 1 | D29: 220 | E29: 230 | F29: 240 | G29: 220 | H29: 219 | I29: 218
B30: Castañas | C30: 2 | D30: 560 | E30: 580 | F30: 550 | G30: 520 | H30: 551 | I30: 550
B35: China Co
B36: 250
B37: 440
B38: 440
B39: 350
B40: 420
B41: 199
